Metadata-Version: 2.1
Name: nadia-proof
Version: 0.1.9
Summary: NADIA is a proof assistant for teaching natural deduction to computer science students. NADIA allows students to write their proofs and automatically checks whether the proofs are correct and, if not, displays any errors found.
Home-page: https://github.com/daviromero/nadia
Author: Davi Romero de Vasconcelos
Author-email: daviromero@ufc.br
License: MIT
Keywords: Natural Deduction,Teaching Logic,Educational Software
Platform: UNKNOWN
License-File: license.txt
